go.py
proJay-1.1.1.dist-info/LICENSE
proJay-1.1.1.dist-info/METADATA
proJay-1.1.1.dist-info/WHEEL
proJay-1.1.1.dist-info/top_level.txt
proJay-1.1.1.dist-info/RECORD
